sqltidy/__init__.py
sqltidy/api.py
sqltidy/cli.py
sqltidy/config_schema.py
sqltidy/core.py
sqltidy/generator.py
sqltidy/pattern_tokenizer.py
sqltidy/plugins.py
sqltidy/rulebook.py
sqltidy/tokenizer.py
sqltidy/dialects/__init__.py
sqltidy/dialects/base.py
sqltidy/dialects/mysql.py
sqltidy/dialects/oracle.py
sqltidy/dialects/postgresql.py
sqltidy/dialects/registry.py
sqltidy/dialects/sqlite.py
sqltidy/dialects/sqlserver.py
sqltidy/patterns/__init__.py
sqltidy/patterns/base.py
sqltidy/patterns/general.py
sqltidy/patterns/matchers.py
sqltidy/patterns/postgres.py
sqltidy/patterns/tsql.py
sqltidy/rules/__init__.py
sqltidy/rules/base.py
sqltidy/rules/general.py
sqltidy/rules/loader.py
sqltidy/rules/sqlserver.py
sqltidy-0.5.0.dist-info/licenses/LICENSE
sqltidy-0.5.0.dist-info/METADATA
sqltidy-0.5.0.dist-info/WHEEL
sqltidy-0.5.0.dist-info/entry_points.txt
sqltidy-0.5.0.dist-info/top_level.txt
sqltidy-0.5.0.dist-info/RECORD
