Metadata-Version: 2.4
Name: sqltidy
Version: 0.5.0
Summary: SQL Formatting Made Easy
Author: Jayden Rasband
Project-URL: Source, https://github.com/jrasband-dev/sqltidy
Project-URL: Documentation, https://jrasband-dev.github.io/sqltidy/
License-File: LICENSE
Requires-Dist: rich
Dynamic: license-file
